README.md
setup.py
pwiener_hello_world.egg-info/PKG-INFO
pwiener_hello_world.egg-info/SOURCES.txt
pwiener_hello_world.egg-info/dependency_links.txt
pwiener_hello_world.egg-info/top_level.txt
sample_package/__init__.py
sample_package/sample.py