Metadata-Version: 2.1
Name: pwiener-hello-world
Version: 1.0.2
Summary: Sample PYPI App
Home-page: UNKNOWN
License: UNKNOWN
Platform: UNKNOWN
